dinstar/__init__.py
dinstar/base.py
dinstar/cdr.py
dinstar/client.py
dinstar/device.py
dinstar/models.py
dinstar/port.py
dinstar/sms.py
dinstar/stk.py
dinstar/ussd.py
dinstar/webhook_models.py
dinstar_uc_api-0.1.0.dist-info/licenses/LICENSE
dinstar_uc_api-0.1.0.dist-info/METADATA
dinstar_uc_api-0.1.0.dist-info/WHEEL
dinstar_uc_api-0.1.0.dist-info/top_level.txt
dinstar_uc_api-0.1.0.dist-info/RECORD
