Metadata-Version: 2.4
Name: dinstar-uc-api
Version: 0.1.0
Summary: A modern Python wrapper for the Dinstar UC Gateway HTTP API (latest version).
Author-email: Vadim Tigin <moucester@gmail.com>
License: MIT
Project-URL: Homepage, https://github.com/moucester/Dinstar-UC-API
Project-URL: Repository, https://github.com/moucester/Dinstar-UC-API
Project-URL: Documentation, https://github.com/moucester/Dinstar-UC-API#readme
Keywords: dinstar,gateway,sms,ussd,api,telecom
Requires-Python: >=3.8
License-File: LICENSE
Requires-Dist: requests>=2.25
Requires-Dist: python-decouple>=3.6
Requires-Dist: pydantic>=1.10
Dynamic: license-file
